tornado_http2/__init__.py
tornado_http2/client.py
tornado_http2/connection.py
tornado_http2/constants.py
tornado_http2/curl.py
tornado_http2/encoding.py
tornado_http2/errors.py
tornado_http2/flow_control.py
tornado_http2/frames.py
tornado_http2/hpack.py
tornado_http2/hpack_huffman_data.txt
tornado_http2/hpack_static_table.txt
tornado_http2/server.py
tornado_http2/stream.py
tornado_http2/test/__init__.py
tornado_http2/test/__main__.py
tornado_http2/test/benchmark.py
tornado_http2/test/encoding_test.py
tornado_http2/test/h2spec_test.py
tornado_http2/test/hpack_test.py
tornado_http2/test/runtests.py
tornado_http2/test/server_test.py
tornado_http2/test/test.crt
tornado_http2/test/test.key
tornado_http2/test/util.py
tornado_http2-0.0.1.dist-info/METADATA
tornado_http2-0.0.1.dist-info/RECORD
tornado_http2-0.0.1.dist-info/WHEEL
tornado_http2-0.0.1.dist-info/top_level.txt
